[
  {
    "id": "post_1776503865841",
    "timestamp": 1776676033424,
    "title": "hello",
    "status": "published",
    "is_pinned": false,
    "content": "आज राजकीय वरिष्ठ माध्यमिक विद्यालय खल्याणी में हिमाचल दिवस, भारत रत्न डॉ. भीमराव अम्बेडकर जयंती तथा बैसाखी के अवसर पर एक विशेष कार्यक्रम का आयोजन किया गया। इस अवसर पर विद्यालय में विविध सांस्कृतिक एवं शैक्षिक गतिविधियाँ आयोजित की गईं, जिनमें विद्यार्थियों ने उत्साहपूर्वक सहभागिता की।\nसांस्कृतिक प्रस्तुतियों का विवरण:\nहिमाचल दिवस (पारंपरिक फैशन शो):\nकक्षा 7वीं एवं 8वीं के विद्यार्थियों—कल्पना, सिमरन-1, सुकन्या, दीप कृतिका, यक्षित, दुष्यंत, अर्पिता, मोनिका, सिमरन-2 तथा प्रमिला—ने हिमाचल प्रदेश की पारंपरिक वेशभूषा में फैशन शो प्रस्तुत किया। उनकी प्रस्तुति सराहनीय रही तथा इससे प्रदेश की सांस्कृतिक विरासत का प्रभावी प्रदर्शन हुआ।\nअम्बेडकर जयंती (स्किट):\nकक्षा 8वीं के विद्यार्थियों द्वारा डॉ. बी.आर. अम्बेडकर के जीवन एवं विचारों पर आधारित एक नाट्य प्रस्तुति दी गई। इसमें करण ने डॉ. अम्बेडकर की मुख्य भूमिका निभाई। अन्य विद्यार्थियों—दुष्यंत, होमन, पारस, पुष्पेंद्र, नमन ठाकुर, दुर्गेश, प्रियाल, सिमरन, गीतांजलि, सोनिया, स्नेहा एवं शिवानी—ने भी अपने अभिनय से प्रस्तुति को प्रभावी बनाया।\nबैसाखी उत्सव (पंजाबी नृत्य):\nकक्षा 7वीं एवं 8वीं की छात्राओं—स्मिता, योग्यता, पलक, नेहा, मोक्षिका एवं राधिका—ने पंजाबी नृत्य प्रस्तुत किया। उनकी प्रस्तुति सुव्यवस्थित एवं सराहनीय रही।\nविशेष प्रस्तुतियाँ:\nकक्षा 9वीं की उर्वशी ने हिमाचल विषय पर कविता पाठ किया तथा हीना ने डॉ. अम्बेडकर के विचारों पर भाषण प्रस्तुत किया।<div><br></div><div><br></div><div>https://youtu.be/mg6HwO7ABPU</div>",
    "media": [
      "media/2026-27_post_1776503865841_pic_01.jpg",
      "media/2026-27_post_1776503865841_pic_04.jpg"
    ]
  }
]